mbox/__init__.py
mbox/cache.py
mbox/click.py
mbox/countries.py
mbox/datetime.py
mbox/itertools.py
mbox/magic.py
mbox/optional.py
mbox/py.typed
mbox/random.py
mbox/requests/__init__.py
mbox/requests/ftp.py
mbox/requests/mock.py
mbox-0.1.11.dist-info/LICENSE
mbox-0.1.11.dist-info/WHEEL
mbox-0.1.11.dist-info/METADATA
mbox-0.1.11.dist-info/RECORD
